jsonteng/__init__.py
jsonteng/element_resolver.py
jsonteng/exception.py
jsonteng/json_loader.py
jsonteng/stats.py
jsonteng/string_resolver.py
jsonteng/tag_resolver.py
jsonteng/template_engine.py
jsonteng/util.py
jsonteng/tags/__init__.py
jsonteng/tags/at_tag.py
jsonteng/tags/exists_tag.py
jsonteng/tags/for_each_tag.py
jsonteng/tags/len_tag.py
jsonteng/tags/one_of_tag.py
jsonteng/tags/tag_base.py
jsonteng/tags/tag_map.py
jsonteng/tags/to_bool_tag.py
jsonteng/tags/to_float_tag.py
jsonteng/tags/to_int_tag.py
jsonteng/tags/to_null_tag.py
jsonteng-1.1.0.dist-info/METADATA
jsonteng-1.1.0.dist-info/WHEEL
jsonteng-1.1.0.dist-info/top_level.txt
jsonteng-1.1.0.dist-info/RECORD
